{
    "nick": "阿愷～下次聚會9月在台北",
    "lastDate": "20_10_23",
    "xpDeque": [
        0,
        1,
        0,
        0,
        1,
        1,
        1,
        1,
        1,
        1,
        1,
        1,
        1,
        1,
        1,
        1,
        1,
        1,
        1,
        1,
        1,
        1,
        1,
        1,
        1,
        1,
        1,
        1,
        1,
        1,
        1,
        1,
        1,
        1,
        1,
        1,
        1,
        1,
        1,
        1,
        1,
        1,
        1,
        1,
        1
    ],
    "xpTotal": 50,
    "eternal": 0
}